LICENSE
setup.py
caph1993_posets.egg-info/PKG-INFO
caph1993_posets.egg-info/SOURCES.txt
caph1993_posets.egg-info/dependency_links.txt
caph1993_posets.egg-info/requires.txt
caph1993_posets.egg-info/top_level.txt
cp93posets/__init__.py
cp93posets/algorithm_floyd_warshall.py
cp93posets/algorithm_random_poset_czech.py
cp93posets/algorithm_tarjan.py
cp93posets/help_index.py
cp93posets/iterators.py
cp93posets/numpy_types.py
cp93posets/outfile.py
cp93posets/poset.py
cp93posets/poset_exceptions.py
cp93posets/poset_wbools.py
cp93posets/posets/__init__.py
cp93posets/posets/covers.py
cp93posets/posets/description.py
cp93posets/posets/endomorphisms.py
cp93posets/posets/external_methods.py
cp93posets/posets/graph_methods.py
cp93posets/posets/graphviz.py
cp93posets/posets/grow_methods.py
cp93posets/posets/hash_methods.py
cp93posets/posets/lattice_methods.py
cp93posets/posets/poset_store.py
cp93posets/posets/posets.py
cp93posets/posets/relations.py